mem_scan/__init__.py
mem_scan/cli.py
mem_scan/monitor.py
mem_scan/scanner.py
mem_scan-1.0.0.dist-info/METADATA
mem_scan-1.0.0.dist-info/WHEEL
mem_scan-1.0.0.dist-info/entry_points.txt
mem_scan-1.0.0.dist-info/RECORD
