Metadata-Version: 2.4
Name: mem-scan
Version: 1.0.0
Summary: A command-line tool for monitoring system and GPU memory usage during process execution
Project-URL: Homepage, https://github.com/NVIDIA/ModelOpt
Project-URL: Repository, https://github.com/NVIDIA/ModelOpt
Project-URL: Issues, https://github.com/NVIDIA/ModelOpt/issues
Author: ModelOpt Team
License-Expression: MIT
Keywords: cli,gpu,memory,monitoring,profiling
Classifier: Development Status :: 4 - Beta
Classifier: Intended Audience :: Developers
Classifier: License :: OSI Approved :: MIT License
Classifier: Operating System :: OS Independent
Classifier: Programming Language :: Python :: 3
Classifier: Programming Language :: Python :: 3.8
Classifier: Programming Language :: Python :: 3.9
Classifier: Programming Language :: Python :: 3.10
Classifier: Programming Language :: Python :: 3.11
Classifier: Programming Language :: Python :: 3.12
Classifier: Topic :: System :: Monitoring
Classifier: Topic :: Utilities
Requires-Python: >=3.8
Requires-Dist: psutil>=5.8.0
Requires-Dist: pynvml>=11.0.0
Provides-Extra: dev
Requires-Dist: black>=22.0.0; extra == 'dev'
Requires-Dist: flake8>=5.0.0; extra == 'dev'
Requires-Dist: mypy>=1.0.0; extra == 'dev'
Requires-Dist: pytest>=7.0.0; extra == 'dev'
